goodboy/__init__.py
goodboy/declarative.py
goodboy/errors.py
goodboy/i18n.py
goodboy/locale/en/LC_MESSAGES/goodboy.mo
goodboy/locale/en/LC_MESSAGES/goodboy.po
goodboy/locale/goodboy.pot
goodboy/locale/ru/LC_MESSAGES/goodboy.mo
goodboy/locale/ru/LC_MESSAGES/goodboy.po
goodboy/messages.py
goodboy/py.typed
goodboy/schema.py
goodboy/types/__init__.py
goodboy/types/dates.py
goodboy/types/dicts.py
goodboy/types/lists.py
goodboy/types/numeric.py
goodboy/types/python.py
goodboy/types/simple.py
goodboy/types/variants.py
goodboy/validator.py
goodboy-0.2.5.dist-info/LICENSE
goodboy-0.2.5.dist-info/METADATA
goodboy-0.2.5.dist-info/WHEEL
goodboy-0.2.5.dist-info/RECORD
