Metadata-Version: 2.1
Name: goodboy
Version: 0.2.5
Summary: Data validation tool
License: MIT
Author: Maxim Andryunin
Author-email: maxim.andryunin@gmail.com
Requires-Python: >=3.7,<4.0
Classifier: License :: OSI Approved :: MIT License
Classifier: Programming Language :: Python :: 3
Classifier: Programming Language :: Python :: 3.7
Classifier: Programming Language :: Python :: 3.8
Classifier: Programming Language :: Python :: 3.9
Classifier: Programming Language :: Python :: 3.10
Classifier: Programming Language :: Python :: 3.11
Classifier: Programming Language :: Python :: 3.12
Requires-Dist: typing-extensions (>=4.0) ; python_version >= "3.6" and python_version < "3.8"
